resources/__init__.py
resources/config.yaml
guardx/__init__.py
guardx/analysis/__init__.py
guardx/analysis/analysis.py
guardx/analysis/specialization/__init__.py
guardx/analysis/specialization/capabilities.py
guardx/analysis/specialization/scripts/__init__.py
guardx/analysis/specialization/scripts/sc_list
guardx/analysis/specialization/specialization.py
guardx/analysis/specialization/types.py
guardx/analysis/specialization/x86_64_tables.py
guardx/analysis/types.py
guardx/config.py
guardx/containers/Dockerfile.analysis
guardx/containers/Dockerfile.sandbox
guardx/containers/Dockerfile.specialization
guardx/containers/__init__.py
guardx/containers/_container.py
guardx/guardx.py
guardx/policy/__init__.py
guardx/policy/types.py
guardx/sandbox/__init__.py
guardx/sandbox/_executor.py
guardx/sandbox/docker_seccomp_default.json
guardx/sandbox/executor.py
guardx/sandbox/stypes.py
guardx/schemas.py
guardx/tools/__init__.py
guardx/tools/cli/__init__.py
guardx/tools/cli/guardx.py
guardx/tools/init.py
guardx-0.2.1.dist-info/METADATA
guardx-0.2.1.dist-info/WHEEL
guardx-0.2.1.dist-info/entry_points.txt
guardx-0.2.1.dist-info/licenses/LICENSE
guardx-0.2.1.dist-info/RECORD
