Metadata-Version: 2.4
Name: guardx
Version: 0.2.1
Summary: A Python library for code analysis and sandboxing
License-File: LICENSE
Author: IBM Research
Requires-Python: >=3.10
Classifier: Programming Language :: Python :: 3
Classifier: Programming Language :: Python :: 3.10
Classifier: Programming Language :: Python :: 3.11
Classifier: Programming Language :: Python :: 3.12
Classifier: Programming Language :: Python :: 3.13
Classifier: Programming Language :: Python :: 3.14
Requires-Dist: docker (>=7.1.0,<8.0.0)
Requires-Dist: pydantic (>=2.7.1,<3.0.0)
Requires-Dist: pyelftools (>=0.31,<0.32)
Requires-Dist: pyseccomp (>=0.1.2,<0.2.0)
Requires-Dist: pyyaml (>=6.0.1,<7.0.0)
Requires-Dist: requests (==2.32.4)
Requires-Dist: urllib3 (==2.5.0)
